{
  "map": {
    "ASMV-1": "task_01KJR2CY3427BQ06FTC55902XZ",
    "ASMV-10": "task_01KJTWP6BR1PYXB1T3MWSK3QC4",
    "ASMV-11": "task_01KJTWP9DQP259SDY8PR25SX8N",
    "ASMV-12": "task_01KJTWPADA2HE6YB8WPH3B6SGZ",
    "ASMV-13": "task_01KJTWPAVND79TGTRVR0B6SESV",
    "ASMV-14": "task_01KJTWPBBYNPSETXTSQMQRM2QB",
    "ASMV-15": "task_01KJTWPBY0BHTGG6G7KP9EQ39C",
    "ASMV-16": "task_01KJTWPD820E7RCK0M6DZHCHVP",
    "ASMV-17": "task_01KJTWPDVAMV3TCETSY64150GS",
    "ASMV-18": "task_01KJTWWBDAHP3TDH2DBC9E5BXT",
    "ASMV-2": "task_01KJR2D9MSRXJDC6Y874T2E0KD",
    "ASMV-3": "task_01KJR2DRR8S64MH1P9V2A86H05",
    "ASMV-4": "task_01KJR2DT7H011JR7N4BB7WVZ02",
    "ASMV-5": "task_01KJR2DWAQEZATQMNTMFRRQGFY",
    "ASMV-6": "task_01KJR2DYVBSCQ0ZHPWX4PEN4FG",
    "ASMV-7": "task_01KJR2ED00JEHAV9ETE998NEQX",
    "ASMV-8": "task_01KJR2EEF23WVYBCD19JM1F35R",
    "ASMV-9": "task_01KJR2EG88NSJBTD9DRT2VEHH2"
  },
  "next_seqs": {
    "ASMV": 19
  },
  "schema_version": 2
}
