{
  "map": {
    "ASMV-1": "task_01KJR2CY3427BQ06FTC55902XZ",
    "ASMV-10": "task_01KJTWP6BR1PYXB1T3MWSK3QC4",
    "ASMV-11": "task_01KJTWP9DQP259SDY8PR25SX8N",
    "ASMV-12": "task_01KJTWPADA2HE6YB8WPH3B6SGZ",
    "ASMV-13": "task_01KJTWPAVND79TGTRVR0B6SESV",
    "ASMV-14": "task_01KJTWPBBYNPSETXTSQMQRM2QB",
    "ASMV-15": "task_01KJTWPBY0BHTGG6G7KP9EQ39C",
    "ASMV-16": "task_01KJTWPD820E7RCK0M6DZHCHVP",
    "ASMV-17": "task_01KJTWPDVAMV3TCETSY64150GS",
    "ASMV-18": "task_01KJTWWBDAHP3TDH2DBC9E5BXT",
    "ASMV-19": "task_01KJZNFN4GPXRCFKNWX5Y7GVBB",
    "ASMV-2": "task_01KJR2D9MSRXJDC6Y874T2E0KD",
    "ASMV-20": "task_01KK2D6PVVR3SS6FFATCNVZ1QK",
    "ASMV-21": "task_01KK2D6R6WVK6JBZB032E30N22",
    "ASMV-22": "task_01KK2D6SGYQTSS26MA46V715H1",
    "ASMV-23": "task_01KK2E1FKF8S47RSQA3GFK022R",
    "ASMV-24": "task_01KK2E1HZH85JN6GCFTBK9XE02",
    "ASMV-25": "task_01KK2E1M9QK21BVSTGQ8MP9AWC",
    "ASMV-26": "task_01KK2E1P08HT9RXT6DGEN56P6D",
    "ASMV-27": "task_01KK2E1RE5EJR4CV42WJKZZYB2",
    "ASMV-28": "task_01KK2E1T6JKVMW979N3XZZR59M",
    "ASMV-29": "task_01KK2E1V6YC15TFPQX3AHN069E",
    "ASMV-3": "task_01KJR2DRR8S64MH1P9V2A86H05",
    "ASMV-30": "task_01KK2E1W3K1WKVATVS1EF720CF",
    "ASMV-31": "task_01KK2E57QRM1QKRC1WYWFPVZ4W",
    "ASMV-32": "task_01KK2E59ZAYQDRPT6JCJZW35C3",
    "ASMV-33": "task_01KK2E5BWEC5NF4YHAR76G4DSG",
    "ASMV-34": "task_01KK2E5DEMQET6J4J9B8QYHX59",
    "ASMV-35": "task_01KK2E5FYA658C6KNTPWZPBJ61",
    "ASMV-36": "task_01KK2E5XJAT6TAN83E0SW8DQ3E",
    "ASMV-37": "task_01KK2EVHYGDBFG9ZK81G6XDV2E",
    "ASMV-38": "task_01KK2EVJJKNF6TDX8KBHFQ3H8H",
    "ASMV-39": "task_01KK2FD0M4TRVSSP0M34EEXXBW",
    "ASMV-4": "task_01KJR2DT7H011JR7N4BB7WVZ02",
    "ASMV-40": "task_01KK2FFH5ZPSKNH991T54JGE5H",
    "ASMV-41": "task_01KK2FPZ2K8602E9YFGD1GZ558",
    "ASMV-42": "task_01KK2GCYHPM1TXNKQ15XCMW881",
    "ASMV-43": "task_01KK2GD2CPE0D84KWZS5FHSQJE",
    "ASMV-44": "task_01KK2GZ6M3MQGFKNY11E0W7W27",
    "ASMV-45": "task_01KK2GZ9528RX1GRGMY6DXPE1M",
    "ASMV-46": "task_01KK2GZD3C1Z8FWMZ61WRCSJ6Y",
    "ASMV-47": "task_01KK2GZGE4ZN558PPYJQ6TRM60",
    "ASMV-48": "task_01KK2HXRJ03KN2R46ZJVJV03EA",
    "ASMV-49": "task_01KK2J2HQX8G3B4EX8DPBJRRXS",
    "ASMV-5": "task_01KJR2DWAQEZATQMNTMFRRQGFY",
    "ASMV-50": "task_01KK2J2NFJJT3WKFS96HA28Q31",
    "ASMV-51": "task_01KK2JTY5BCZZ9EC463XKQ1NNT",
    "ASMV-52": "task_01KK2KTZ5XXHFXCZP3MEN3S6FD",
    "ASMV-53": "task_01KK2XGPK1DFR5JQMR5G1YA62K",
    "ASMV-6": "task_01KJR2DYVBSCQ0ZHPWX4PEN4FG",
    "ASMV-7": "task_01KJR2ED00JEHAV9ETE998NEQX",
    "ASMV-8": "task_01KJR2EEF23WVYBCD19JM1F35R",
    "ASMV-9": "task_01KJR2EG88NSJBTD9DRT2VEHH2"
  },
  "next_seqs": {
    "ASMV": 54
  },
  "schema_version": 2
}
